{
  "nightly": {
    "description": "develop/v4-nightly",
    "hide": false,
    "last_updated": "2025-12-20T12:56:34.000Z",
    "last_updated_url": "https://github.com/hotio/sonarr/actions/runs/20394553644",
    "latest": false,
    "tags": [
      "nightly",
      "nightly-4.0.16.2943",
      "nightly-3f2c91e"
    ]
  },
  "release": {
    "description": "main/v4-stable",
    "hide": false,
    "last_updated": "2025-12-20T12:58:37.000Z",
    "last_updated_url": "https://github.com/hotio/sonarr/actions/runs/20394553702",
    "latest": true,
    "tags": [
      "release",
      "release-4.0.16.2944",
      "release-ba002be"
    ]
  }
}
